Products.PythonScripts-5.1-py3.11-nspkg.pth
Products/PythonScripts/PythonScript.py
Products/PythonScripts/Utility.py
Products/PythonScripts/__init__.py
Products/PythonScripts/configure.zcml
Products/PythonScripts/standard.py
Products/PythonScripts/Extensions/RemotePS.py
Products/PythonScripts/tests/__init__.py
Products/PythonScripts/tests/testBindings.py
Products/PythonScripts/tests/testPythonScript.py
Products/PythonScripts/tests/tscripts/big_boolean.ps
Products/PythonScripts/tests/tscripts/boolean_map.ps
Products/PythonScripts/tests/tscripts/class.__name__.ps
Products/PythonScripts/tests/tscripts/complete.ps
Products/PythonScripts/tests/tscripts/complex_print.ps
Products/PythonScripts/tests/tscripts/fibonacci.ps
Products/PythonScripts/tests/tscripts/filepath.ps
Products/PythonScripts/tests/tscripts/for_loop.ps
Products/PythonScripts/tests/tscripts/global_is_declaration.ps
Products/PythonScripts/tests/tscripts/mutate_literals.ps
Products/PythonScripts/tests/tscripts/ns_bind.ps
Products/PythonScripts/tests/tscripts/ns_bind_invalid.ps
Products/PythonScripts/tests/tscripts/simple_print.ps
Products/PythonScripts/tests/tscripts/subversive_except.ps
Products/PythonScripts/tests/tscripts/try_except.ps
Products/PythonScripts/tests/tscripts/tuple_unpack_assignment.ps
Products/PythonScripts/tests/tscripts/while_loop.ps
Products/PythonScripts/www/default_content
Products/PythonScripts/www/pyScriptAdd.dtml
Products/PythonScripts/www/pyScriptEdit.dtml
Products/PythonScripts/www/pyScriptProxy.dtml
Products.PythonScripts-5.1.dist-info/LICENSE.txt
Products.PythonScripts-5.1.dist-info/METADATA
Products.PythonScripts-5.1.dist-info/WHEEL
Products.PythonScripts-5.1.dist-info/entry_points.txt
Products.PythonScripts-5.1.dist-info/namespace_packages.txt
Products.PythonScripts-5.1.dist-info/top_level.txt
Products.PythonScripts-5.1.dist-info/RECORD
