Metadata-Version: 2.1
Name: Products.PythonScripts
Version: 5.1
Summary: Provides support for restricted execution of Python scripts in Zope.
Home-page: https://github.com/zopefoundation/Products.PythonScripts
Author: Zope Foundation and Contributors
Author-email: zope-dev@zope.dev
License: ZPL 2.1
Project-URL: Issue Tracker, https://github.com/zopefoundation/Products.PythonScripts/issues
Project-URL: Sources, https://github.com/zopefoundation/Products.PythonScripts
Classifier: Development Status :: 6 - Mature
Classifier: Environment :: Web Environment
Classifier: Framework :: Zope
Classifier: Framework :: Zope :: 5
Classifier: License :: OSI Approved :: Zope Public License
Classifier: Operating System :: OS Independent
Classifier: Programming Language :: Python
Classifier: Programming Language :: Python :: 3
Classifier: Programming Language :: Python :: 3.8
Classifier: Programming Language :: Python :: 3.9
Classifier: Programming Language :: Python :: 3.10
Classifier: Programming Language :: Python :: 3.11
Classifier: Programming Language :: Python :: 3.12
Classifier: Programming Language :: Python :: 3.13
Classifier: Programming Language :: Python :: Implementation :: CPython
Requires-Python: >=3.8
License-File: LICENSE.txt
Requires-Dist: setuptools
Requires-Dist: AccessControl
Requires-Dist: Acquisition
Requires-Dist: DateTime
Requires-Dist: DocumentTemplate
Requires-Dist: RestrictedPython >=4.0b5
Requires-Dist: zExceptions
Requires-Dist: Zope >=4.1.2
